onelog/__init__.py
onelog/html_renderer.py
onelog/logger.py
onelog/templates/report.html
onelog-0.2.0.dist-info/METADATA
onelog-0.2.0.dist-info/WHEEL
onelog-0.2.0.dist-info/RECORD
