Metadata-Version: 2.4
Name: onelog
Version: 0.2.0
Summary: Simple AI Logging
Author-email: Maximilian Wessendorf <maxi-git@outlook.de>
License: MIT
Requires-Python: >=3.12
Requires-Dist: jinja2>=3.0.0
Requires-Dist: numpy>=2.3.1
Requires-Dist: pillow>=11.3.0
